setup.py
fake_open/__init__.py
fake_open/fake_open.py
fake_open.egg-info/PKG-INFO
fake_open.egg-info/SOURCES.txt
fake_open.egg-info/dependency_links.txt
fake_open.egg-info/requires.txt
fake_open.egg-info/top_level.txt