Metadata-Version: 1.1
Name: fake-open
Version: 0.0.1
Summary: fake-open: Library for testing opening writable files.
Home-page: https://git.lumc.nl/j.f.j.laros/fake-open
Author: LUMC, Jeroen F.J. Laros
Author-email: J.F.J.Laros@lumc.nl
License: MIT License
Platform: any
Classifier: Development Status :: 3 - Alpha
Classifier: Intended Audience :: Science/Research
Classifier: Intended Audience :: Developers
Classifier: Topic :: Scientific/Engineering
Classifier: License :: OSI Approved :: MIT License
Classifier: Operating System :: OS Independent
Classifier: Programming Language :: Python
Classifier: Programming Language :: Python :: 2
Classifier: Programming Language :: Python :: 3
Classifier: Programming Language :: Python :: 2.7
Classifier: Programming Language :: Python :: 3.3
Classifier: Programming Language :: Python :: 3.4
